[
{"text": ["Физика. Геометрическая оптика: Законы преломления. Центр онлайн-обучения «Фоксфорд»"], "author": ["Онлайн-школа с 3 по 11 класс"], "url": "https://www.youtube.com/watch?v=cMBrpdpOAfU"},
{"text": ["Эмиль Ахмедов: \"Оптика и квантовая механика\""], "author": ["Центр Архэ"], "url": "https://www.youtube.com/watch?v=NayWtS53NNU"},
{"text": ["Опыт Юнга. Волновая оптика. (Макар Светлый)"], "author": ["Макар Светлый"], "url": "https://www.youtube.com/watch?v=p3ffGBh6Rbo"},
{"text": ["\"Познавательный фильм\": Оптика"], "author": ["Москва 24"], "url": "https://www.youtube.com/watch?v=5RScf8JgCZQ"},
{"text": ["Урок 412. Скорость света и ее измерение"], "author": ["Павел ВИКТОР"], "url": "https://www.youtube.com/watch?v=6LSiaeIC6m4&list=PLYLAAGsAQhw9nEvX4BxcRMTRffGvIzMis"},
{"text": ["ПОСП 4-8Х42 Надежная оптика на отечественные карабины"], "author": ["Optivisions TV"], "url": "https://www.youtube.com/watch?v=KjTkwVJ5z9Q"},
{"text": ["Геометрическая оптика"], "author": ["Edu Spb"], "url": "https://www.youtube.com/watch?v=lbJ6gUGQOJI"},
{"text": ["Урок 413. Интерференция света"], "author": ["Павел ВИКТОР"], "url": "https://www.youtube.com/watch?v=0MuRk7X-vIM&list=PLYLAAGsAQhw9nEvX4BxcRMTRffGvIzMis"},
{"text": ["супер крутая и дешёвая оптика из китая! LEUPOLD MARK4"], "author": ["китайский дракон"], "url": "https://www.youtube.com/watch?v=AaplLe2x6gU"},
{"text": ["Diffused light - Physics in experiments"], "author": ["GetAClass - Физика в опытах и экспериментах"], "url": "https://www.youtube.com/watch?v=BzIpUwBcFV8&list=PLeOlm2kq0HcuZp7qtgSok-jDYx9L_bpjx"},
{"text": ["Суперглаз. АРМЕЙСКАЯ ОПТИКА. Ударная сила"], "author": ["Документалистика РФ"], "url": "https://www.youtube.com/watch?v=xTn49hUfZvM"},
{"text": ["Light rays - Physics in experiments"], "author": ["GetAClass - Физика в опытах и экспериментах"], "url": "https://www.youtube.com/watch?v=VdSsgDQf-fM&list=PLeOlm2kq0HcuZp7qtgSok-jDYx9L_bpjx"},
{"text": ["LED подфарники, Дополнительная оптика!"], "author": ["Жизнь Нивы Урбан"], "url": "https://www.youtube.com/watch?v=b7CrWEDEqyA"},
{"text": ["Бюджетная оптика на АК"], "author": ["YarSO"], "url": "https://www.youtube.com/watch?v=a49rRNJzHwI"},
{"text": ["Оптика. Свет - природа и свойства"], "author": ["Учебное видео"], "url": "https://www.youtube.com/watch?v=mdiEJcYsIOM"},
{"text": ["Подготовка к ЕГЭ по физике. Лекция №5. Волновая оптика"], "author": ["Михаил Пенкин"], "url": "https://www.youtube.com/watch?v=DVG5DaPWNZo"},
{"text": ["Бешеная оптика, блокировка и силовой бампер на Фронтеру."], "author": ["AcademeG"], "url": "https://www.youtube.com/watch?v=yNrSeyrK17Y"},
{"text": ["Физика: подготовка к ОГЭ и ЕГЭ. Геометрическая оптика. Тонкие линзы"], "author": ["Timetostudy Сourses"], "url": "https://www.youtube.com/watch?v=s4HqOz_L7Js"},
{"text": ["Геометрическая оптика основные понятия"], "author": ["gennadiy2012"], "url": "https://www.youtube.com/watch?v=3AStnjyCCwM"},
{"text": ["Физика: подготовка к ОГЭ и ЕГЭ. Геометрическая оптика. Законы отражения и преломления света"], "author": ["Timetostudy Сourses"], "url": "https://www.youtube.com/watch?v=7jHZI3X0Rr4"},
{"text": ["Волновая оптика"], "author": ["Science Lite"], "url": "https://www.youtube.com/watch?v=4nLzvBKEIXQ"},
{"text": ["Урок 390. Законы геометрической оптики - 1"], "author": ["Павел ВИКТОР"], "url": "https://www.youtube.com/watch?v=LVziS9Fkrb4&list=PLYLAAGsAQhw-t-V-oTSJBemkt9gysB8xE"},
{"text": ["Урок 391. Законы геометрической оптики - 2"], "author": ["Павел ВИКТОР"], "url": "https://www.youtube.com/watch?v=df1npELwAiU&list=PLYLAAGsAQhw-t-V-oTSJBemkt9gysB8xE"}
]